{
  "levels": [
    { "op": "add", "max": 0 },
    { "op": "add", "max": 1 },
    { "op": "add", "max": 2 },
    { "op": "add", "max": 3 },
    { "op": "add", "max": 4 },
    { "op": "add", "max": 5 },
    { "op": "add", "max": 6 },
    { "op": "add", "max": 7 },
    { "op": "add", "max": 8 },
    { "op": "add", "max": 9 },
    { "op": "add", "max": 10 },
    { "op": "sub", "max": 0 },
    { "op": "sub", "max": 1 },
    { "op": "sub", "max": 2 },
    { "op": "sub", "max": 3 },
    { "op": "sub", "max": 4 },
    { "op": "sub", "max": 5 },
    { "op": "sub", "max": 6 },
    { "op": "sub", "max": 7 },
    { "op": "sub", "max": 8 },
    { "op": "sub", "max": 9 },
    { "op": "sub", "max": 10 },
    { "op": "mix", "max": 0 },
    { "op": "mix", "max": 1 },
    { "op": "mix", "max": 2 },
    { "op": "mix", "max": 3 },
    { "op": "mix", "max": 4 },
    { "op": "mix", "max": 5 },
    { "op": "mix", "max": 6 },
    { "op": "mix", "max": 7 },
    { "op": "mix", "max": 8 },
    { "op": "mix", "max": 9 },
    { "op": "mix", "max": 10 }
  ]
}
